[
  {
    "id": "66666666-1113-0000-0000-000000000001",
    "code": "jpd113",
    "title": "Tiếng Nhật Sơ Cấp 1",
    "description": "Từ vựng cho khóa JPD113",
    "lessonCount": 9,
    "wordCount": 337,
    "learnedCount": 0,
    "practicedCount": 0
  },
  {
    "id": "66666666-1123-0000-0000-000000000001",
    "code": "jpd123",
    "title": "Tiếng Nhật Sơ Cấp 2",
    "description": "Từ vựng cho khóa JPD123",
    "lessonCount": 12,
    "wordCount": 251,
    "learnedCount": 0,
    "practicedCount": 0
  }
]
